sight_api/__init__.py
sight_api-1.2.0.dist-info/LICENSE
sight_api-1.2.0.dist-info/WHEEL
sight_api-1.2.0.dist-info/METADATA
sight_api-1.2.0.dist-info/RECORD
