Metadata-Version: 2.1
Name: sight-api
Version: 1.2.0
Summary: Official client for Siftrics' Sight API, which is a text recognition service
Home-page: https://siftrics.com/
Keywords: sight,api,text,recognition,ocr,computer,vision,siftrics
Author: Siftrics Founder
Author-email: siftrics@siftrics.com
Requires-Python: >=2.7, !=3.0.*, !=3.1.*, !=3.2.*, !=3.3.*, !=3.4.*
Classifier: Programming Language :: Python :: 2
Classifier: Programming Language :: Python :: 2.7
Classifier: Programming Language :: Python :: 3
Classifier: Programming Language :: Python :: 3.5
Classifier: Programming Language :: Python :: 3.6
Classifier: Programming Language :: Python :: 3.7
Classifier: Programming Language :: Python :: 3.8
Requires-Dist: requests (>=2.23.0,<3.0.0)
Project-URL: Repository, https://github.com/siftrics/sight-python
